examples/__init__.py
examples/api_text_generation.py
examples/audio_analysis.py
examples/config.py
examples/csv_analysis.py
examples/deep_search.py
examples/image_analysis.py
examples/image_editing.py
examples/image_generation.py
examples/pdf_analysis.py
examples/search.py
examples/text_generation.py
examples/thinking_generation.py
examples/txt_analysis.py
examples/video_analysis.py
examples/youtube_analysis.py
mindbot/__init__.py
mindbot/audio.py
mindbot/client.py
mindbot/image.py
mindbot/search.py
mindbot/text.py
mindbot/vision.py
testmindbotaiaia-1.6.0.dist-info/LICENSE
testmindbotaiaia-1.6.0.dist-info/METADATA
testmindbotaiaia-1.6.0.dist-info/WHEEL
testmindbotaiaia-1.6.0.dist-info/top_level.txt
testmindbotaiaia-1.6.0.dist-info/RECORD
